LICENSE
README.md
setup.py
./ms_active_directory/__init__.py
./ms_active_directory/exceptions.py
./ms_active_directory/logging_utils.py
./ms_active_directory/core/__init__.py
./ms_active_directory/core/ad_domain.py
./ms_active_directory/core/ad_kerberos_keys.py
./ms_active_directory/core/ad_objects.py
./ms_active_directory/core/ad_session.py
./ms_active_directory/core/managed_ad_objects.py
./ms_active_directory/environment/__init__.py
./ms_active_directory/environment/constants.py
./ms_active_directory/environment/format_utils.py
./ms_active_directory/environment/discovery/__init__.py
./ms_active_directory/environment/discovery/discovery_constants.py
./ms_active_directory/environment/discovery/discovery_utils.py
./ms_active_directory/environment/kerberos/__init__.py
./ms_active_directory/environment/kerberos/kerberos_client_configurer.py
./ms_active_directory/environment/kerberos/kerberos_constants.py
./ms_active_directory/environment/kerberos/kerberos_keytab_generator.py
./ms_active_directory/environment/kerberos/kerberos_keytab_ingester.py
./ms_active_directory/environment/kerberos/kerberos_raw_key_generator.py
./ms_active_directory/environment/ldap/__init__.py
./ms_active_directory/environment/ldap/ldap_constants.py
./ms_active_directory/environment/ldap/ldap_format_utils.py
./ms_active_directory/environment/ldap/trust_constants.py
./ms_active_directory/environment/security/__init__.py
./ms_active_directory/environment/security/ad_security_guids.py
./ms_active_directory/environment/security/security_config_constants.py
./ms_active_directory/environment/security/security_config_utils.py
./ms_active_directory/environment/security/security_descriptor_utils.py
ms_active_directory.egg-info/PKG-INFO
ms_active_directory.egg-info/SOURCES.txt
ms_active_directory.egg-info/dependency_links.txt
ms_active_directory.egg-info/requires.txt
ms_active_directory.egg-info/top_level.txt